odoo/addons/product_harmonized_system_tax_rate/README.rst
odoo/addons/product_harmonized_system_tax_rate/__init__.py
odoo/addons/product_harmonized_system_tax_rate/__manifest__.py
odoo/addons/product_harmonized_system_tax_rate/i18n/it.po
odoo/addons/product_harmonized_system_tax_rate/i18n/product_harmonized_system_tax_rate.pot
odoo/addons/product_harmonized_system_tax_rate/models/__init__.py
odoo/addons/product_harmonized_system_tax_rate/models/hs_code.py
odoo/addons/product_harmonized_system_tax_rate/models/hs_code_tax_rate.py
odoo/addons/product_harmonized_system_tax_rate/models/product.py
odoo/addons/product_harmonized_system_tax_rate/readme/CONTRIBUTORS.md
odoo/addons/product_harmonized_system_tax_rate/readme/CREDITS.md
odoo/addons/product_harmonized_system_tax_rate/readme/DESCRIPTION.md
odoo/addons/product_harmonized_system_tax_rate/readme/USAGE.md
odoo/addons/product_harmonized_system_tax_rate/security/ir.model.access.csv
odoo/addons/product_harmonized_system_tax_rate/static/description/icon.png
odoo/addons/product_harmonized_system_tax_rate/static/description/index.html
odoo/addons/product_harmonized_system_tax_rate/views/hs_code_tax_rate_views.xml
odoo/addons/product_harmonized_system_tax_rate/views/hs_code_views.xml
odoo/addons/product_harmonized_system_tax_rate/views/product_views.xml
odoo_addon_product_harmonized_system_tax_rate-18.0.1.0.0.4.dist-info/METADATA
odoo_addon_product_harmonized_system_tax_rate-18.0.1.0.0.4.dist-info/WHEEL
odoo_addon_product_harmonized_system_tax_rate-18.0.1.0.0.4.dist-info/top_level.txt
odoo_addon_product_harmonized_system_tax_rate-18.0.1.0.0.4.dist-info/RECORD
