Metadata-Version: 2.1
Name: odoo-addon-product_harmonized_system_tax_rate
Version: 18.0.1.0.0.4
Requires-Python: >=3.10
Requires-Dist: odoo-addon-product_harmonized_system_stock==18.0.*
Requires-Dist: odoo==18.0.*
Summary: Add a notion of tax rate linked to an H.S. Code and Country.
Home-page: https://github.com/OCA/intrastat-extrastat
License: AGPL-3
Author: Akretion, Odoo Community Association (OCA)
Author-email: support@odoo-community.org
Classifier: Programming Language :: Python
Classifier: Framework :: Odoo
Classifier: Framework :: Odoo :: 18.0
Classifier: License :: OSI Approved :: GNU Affero General Public License v3
